ics_query/__init__.py
ics_query/__main__.py
ics_query/_version.py
ics_query/cli.py
ics_query/parse.py
ics_query/query.py
ics_query/version.py
ics_query/tests/__init__.py
ics_query/tests/conftest.py
ics_query/tests/test_command_line.py
ics_query/tests/test_issue_40_valid_calendar.py
ics_query/tests/test_parse_date.py
ics_query/tests/test_parse_timedelta.py
ics_query/tests/runs/all --tz Singapore one-event.ics -.run
ics_query/tests/runs/all -c VALARM alarm_1_week_before_event.ics -.run
ics_query/tests/runs/all three-events.ics -.run
ics_query/tests/runs/at 2014-05-03 x-wr-timezone-rdate-hackerpublicradio.ics -.run
ics_query/tests/runs/at 2019-03-04 multiple-calendars.ics -.run
ics_query/tests/runs/at 2019-03-04 one-event-twice.ics -.run
ics_query/tests/runs/at 2019-03-04 one-event.ics -.run
ics_query/tests/runs/at 2019-03-07 multiple-calendars.ics -.run
ics_query/tests/runs/at 2024-08-20 Berlin-Los-Angeles.ics -.run
ics_query/tests/runs/between 20240823 4d recurring-work-events.ics -.run
ics_query/tests/runs/first -c VJOURNAL -c VEVENT one-event.ics -.run
ics_query/tests/runs/first -c VJOURNAL one-event.ics -.run
ics_query/tests/runs/first -c VJOURNAL simple-journal.ics -.run
ics_query/tests/runs/first -c VTODO -c VJOURNAL simple-todo.ics -.run
ics_query/tests/runs/first -c VTODO simple-todo.ics -.run
ics_query/tests/runs/first empty-calendar.ics -.run
ics_query/tests/runs/first empty-file.ics -.run
ics_query/tests/runs/first recurring-work-events.ics -.run
ics_query/tests/runs/calendars/Berlin-Los-Angeles.ics
ics_query/tests/runs/calendars/alarm_1_week_before_event.ics
ics_query/tests/runs/calendars/empty-calendar.ics
ics_query/tests/runs/calendars/empty-file.ics
ics_query/tests/runs/calendars/multiple-calendars.ics
ics_query/tests/runs/calendars/one-event-twice.ics
ics_query/tests/runs/calendars/one-event-without-timezone.ics
ics_query/tests/runs/calendars/one-event.ics
ics_query/tests/runs/calendars/recurring-work-events.ics
ics_query-0.4.49.dist-info/METADATA
ics_query-0.4.49.dist-info/WHEEL
ics_query-0.4.49.dist-info/entry_points.txt
ics_query-0.4.49.dist-info/licenses/LICENSE
ics_query-0.4.49.dist-info/RECORD
