Metadata-Version: 2.4
Name: ics-query
Version: 0.4.49
Summary: Find out what happens in ICS calendar files - query and filter RFC 5545 compatible .ics files for events, journals, TODOs and more.
Project-URL: Homepage, https://github.com/niccokunzmann/ics-query/
Project-URL: Repository, https://github.com/niccokunzmann/ics-query/
Project-URL: source_archive, https://github.com/niccokunzmann/ics-query/archive/767c57a9a9769a834fe72e02bd910c3637df3d6c.zip
Project-URL: Issues, https://github.com/niccokunzmann/ics-query/issues
Project-URL: Documentation, https://github.com/niccokunzmann/ics-query/
Project-URL: Changelog, https://github.com/niccokunzmann/ics-query/#changelog
Author-email: Nicco Kunzmann <niccokunzmann@rambler.ru>
Maintainer-email: Nicco Kunzmann <niccokunzmann@rambler.ru>
License:                     GNU GENERAL PUBLIC LICENSE
License-File: LICENSE
Keywords: calendar,command line,icalendar,ics,rfc5545,scheduling
Classifier: Development Status :: 5 - Production/Stable
Classifier: Intended Audience :: Developers
Classifier: License :: OSI Approved :: GNU General Public License v3 or later (GPLv3+)
Classifier: Operating System :: OS Independent
Classifier: Programming Language :: Python :: 3.9
Classifier: Programming Language :: Python :: 3.10
Classifier: Programming Language :: Python :: 3.11
Classifier: Programming Language :: Python :: 3.12
Classifier: Programming Language :: Python :: 3.13
Classifier: Topic :: Office/Business :: Scheduling
Requires-Python: >=3.9
Requires-Dist: click==8.1.8
Requires-Dist: icalendar==6.3.2
Requires-Dist: python-dateutil==2.9.0.post0
Requires-Dist: recurring-ical-events==3.8.0
Requires-Dist: six==1.17.0
Requires-Dist: tzdata==2025.3
Requires-Dist: tzlocal==5.3.1
Requires-Dist: x-wr-timezone==2.0.1
Provides-Extra: test
Requires-Dist: pytest; extra == 'test'
